dok2any/__init__.py
dok2any/converter.py
dok2any-0.1.0.dist-info/LICENSE
dok2any-0.1.0.dist-info/METADATA
dok2any-0.1.0.dist-info/WHEEL
dok2any-0.1.0.dist-info/entry_points.txt
dok2any-0.1.0.dist-info/top_level.txt
dok2any-0.1.0.dist-info/RECORD
