Metadata-Version: 2.1
Name: dok2any
Version: 0.1.0
Summary: A package to convert DOK files to various formats
Home-page: https://github.com/dulaanr97/dok2any
Author: Dulaj Ramanayaka
Author-email: dulajnr97git@gmail.com
Classifier: Programming Language :: Python :: 3
Classifier: License :: OSI Approved :: MIT License
Classifier: Operating System :: OS Independent
Requires-Python: >=3.10
License-File: LICENSE
Requires-Dist: openbabel
